shoobx/__init__.py
shoobx/rml2odt/__init__.py
shoobx/rml2odt/directive.py
shoobx/rml2odt/document.py
shoobx/rml2odt/flowable.py
shoobx/rml2odt/interfaces.py
shoobx/rml2odt/list.py
shoobx/rml2odt/rml2odt.py
shoobx/rml2odt/stylesheet.py
shoobx/rml2odt/table.py
shoobx/rml2odt/template.py
shoobx/rml2odt/tests/__init__.py
shoobx/rml2odt/tests/test_flowable.py
shoobx/rml2odt/tests/test_rml2odt.py
shoobx/rml2odt/tests/test_table.py
shoobx/rml2odt/tests/test_data/expected/comments.odt
shoobx/rml2odt/tests/test_data/expected/hello-world.odt
shoobx/rml2odt/tests/test_data/expected/numberingTest.odt
shoobx/rml2odt/tests/test_data/expected/tag-blockTable-1.odt
shoobx/rml2odt/tests/test_data/expected/tag-blockTable-KeepTogether.odt
shoobx/rml2odt/tests/test_data/expected/tag-blockTable-bulkData.odt
shoobx/rml2odt/tests/test_data/expected/tag-blockTable-list.odt
shoobx/rml2odt/tests/test_data/expected/tag-blockTable-nested.odt
shoobx/rml2odt/tests/test_data/expected/tag-blockTable-noKeepTogether.odt
shoobx/rml2odt/tests/test_data/expected/tag-blockTableStyle-border.odt
shoobx/rml2odt/tests/test_data/expected/tag-blockTableStyle-fancy.odt
shoobx/rml2odt/tests/test_data/expected/tag-blockTableStyle-span.odt
shoobx/rml2odt/tests/test_data/expected/tag-blockTableStyle-zebra.odt
shoobx/rml2odt/tests/test_data/expected/tag-blockTableStyle.odt
shoobx/rml2odt/tests/test_data/expected/tag-br.odt
shoobx/rml2odt/tests/test_data/expected/tag-color.odt
shoobx/rml2odt/tests/test_data/expected/tag-header-footer-main.odt
shoobx/rml2odt/tests/test_data/expected/tag-header-footer.odt
shoobx/rml2odt/tests/test_data/expected/tag-hr.odt
shoobx/rml2odt/tests/test_data/expected/tag-image.odt
shoobx/rml2odt/tests/test_data/expected/tag-para-base.odt
shoobx/rml2odt/tests/test_data/expected/tag-para-char-styling.odt
shoobx/rml2odt/tests/test_data/expected/tag-para-whitespace.odt
shoobx/rml2odt/tests/test_data/expected/tag-paraStyle.odt
shoobx/rml2odt/tests/test_data/expected/tag-ul-ol-li.odt
shoobx.rml2odt-0.9.0.dist-info/AUTHORS.txt
shoobx.rml2odt-0.9.0.dist-info/LICENSE.txt
shoobx.rml2odt-0.9.0.dist-info/METADATA
shoobx.rml2odt-0.9.0.dist-info/WHEEL
shoobx.rml2odt-0.9.0.dist-info/entry_points.txt
shoobx.rml2odt-0.9.0.dist-info/top_level.txt
shoobx.rml2odt-0.9.0.dist-info/RECORD
