Metadata-Version: 2.1
Name: shoobx.rml2odt
Version: 0.9.0
Summary: A converter from RML to ODT.
Home-page: http://pypi.python.org/pypi/shoobx.rml2odt
Author: Shoobx, Inc.
Author-email: dev@shoobx.com
License: ZPL 2.1
Keywords: rml odf odt libreoffice pagetemplate
Classifier: Development Status :: 4 - Beta
Classifier: Intended Audience :: Developers
Classifier: License :: OSI Approved :: Zope Public License
Classifier: Programming Language :: Python
Classifier: Programming Language :: Python :: 3
Classifier: Programming Language :: Python :: 3.7
Classifier: Programming Language :: Python :: 3.8
Classifier: Programming Language :: Python :: 3.9
Classifier: Programming Language :: Python :: 3.10
Classifier: Programming Language :: Python :: 3.11
Classifier: Programming Language :: Python :: Implementation :: CPython
Classifier: Natural Language :: English
Classifier: Operating System :: OS Independent
License-File: LICENSE.txt
License-File: AUTHORS.txt
Requires-Dist: lazy
Requires-Dist: odfpy
Requires-Dist: importlib-metadata
Requires-Dist: pypng
Requires-Dist: PyQRCode
Requires-Dist: setuptools
Requires-Dist: z3c.rml
Requires-Dist: zope.interface
Provides-Extra: test
Requires-Dist: coverage ; extra == 'test'
Requires-Dist: unoconv ; extra == 'test'
Requires-Dist: zope.testrunner ; extra == 'test'
